detectshift/__init__.py
detectshift/cdist.py
detectshift/tests.py
detectshift/tools.py
detectshift-1.0.1.dist-info/LICENSE
detectshift-1.0.1.dist-info/METADATA
detectshift-1.0.1.dist-info/WHEEL
detectshift-1.0.1.dist-info/top_level.txt
detectshift-1.0.1.dist-info/RECORD
