Metadata-Version: 2.1
Name: detectshift
Version: 1.0.1
Summary: DetectShift: A unified framework for dataset shift diagnostics
Home-page: https://github.com/felipemaiapolo/detectshift
Author: Felipe Maia Polo
Author-email: felipemaiapolo@gmail.com
Classifier: Programming Language :: Python :: 3
Classifier: License :: OSI Approved :: MIT License
Classifier: Operating System :: OS Independent
License-File: LICENSE
Requires-Dist: numpy
Requires-Dist: pandas
Requires-Dist: sklearn
Requires-Dist: tqdm
Requires-Dist: catboost
